jupic_toolkit/__init__.py
jupic_toolkit/__main__.py
jupic_toolkit/grader/__init__.py
jupic_toolkit/grader/c1.py
jupic_toolkit/grader/c10.py
jupic_toolkit/grader/c2.py
jupic_toolkit/grader/c3.py
jupic_toolkit/grader/c4.py
jupic_toolkit/grader/c5.py
jupic_toolkit/grader/c6.py
jupic_toolkit/grader/c7.py
jupic_toolkit/grader/c8.py
jupic_toolkit/grader/c9.py
jupic_toolkit/grader/grader.py
jupic_toolkit/json/__init__.py
jupic_toolkit/json/writer.py
jupic_toolkit/jupic.py
jupic_toolkit-0.0.5.dist-info/LICENSE
jupic_toolkit-0.0.5.dist-info/WHEEL
jupic_toolkit-0.0.5.dist-info/METADATA
jupic_toolkit-0.0.5.dist-info/RECORD
